[
    {
        "title": "[서울] 2024 이찬원 콘서트 ‘ 찬가（燦歌）’",
        "ImageURL": "http://tkfile.yes24.com/upload2/perfblog/202405/20240502/20240502-49577.jpg",
        "Venue": "2024.06.08~2024.06.09KSPO DOME(올림픽체조경기장)",
        "rank": "1위"
    },
    {
        "title": "[전주] 나훈아 ‘2024 고마웠습니다-라스트 콘서트(LAST CONCERT)’",
        "ImageURL": "http://tkfile.yes24.com/upload2/perfblog/202404/20240425/20240425-49277.jpg",
        "Venue": "2024.07.06~2024.07.06전주 실내체육관",
        "rank": "2위"
    },
    {
        "title": "BAE173 2nd FAN CONCERT : POLARIS",
        "ImageURL": "http://tkfile.yes24.com/upload2/perfblog/202404/20240418/20240418-49437_1.jpg",
        "Venue": "2024.05.25~2024.05.26세종대학교 대양홀",
        "rank": "3위"
    },
    {
        "title": "2024 BAEKHO ＆ BIGONE CONCERT 〈우리樂〉",
        "ImageURL": "http://tkfile.yes24.com/upload2/perfblog/202404/20240430/20240430-49621.jpg",
        "Venue": "2024.05.18~2024.05.18예스24 원더로크홀",
        "rank": "4위"
    },
    {
        "title": "SHINee WORLD Ⅵ [PERFECT ILLUMINATION : SHINee’S BACK]",
        "ImageURL": "http://tkfile.yes24.com/upload2/perfblog/202404/20240419/20240419-49438.jpg",
        "Venue": "2024.05.24~2024.05.26INSPIRE ARENA(인스파이어 아레나)",
        "rank": "5위"
    },
    {
        "title": "[대구] LIVE ON 로이킴X김필",
        "ImageURL": "http://tkfile.yes24.com/upload2/perfblog/202404/20240422/20240422-49517.jpg",
        "Venue": "2024.06.01~2024.06.01영남대학교 천마아트센터 그랜드홀",
        "rank": "6위"
    },
    {
        "title": "HAVE A NICE TRIP 2024",
        "ImageURL": "http://tkfile.yes24.com/upload2/perfblog/202404/20240430/20240430-49358_1.jpg",
        "Venue": "2024.07.27~2024.07.28킨텍스 제2전시장 7,8홀",
        "rank": "7위"
    },
    {
        "title": "특전소녀전선 스프링리그",
        "ImageURL": "http://tkfile.yes24.com/upload2/perfblog/202403/20240327/20240327-49263.jpg",
        "Venue": "2024.04.04~2024.05.19예스24 원더로크홀",
        "rank": "8위"
    },
    {
        "title": "[여수] 2024 김창옥 토크콘서트 시즌4",
        "ImageURL": "http://tkfile.yes24.com/upload2/perfblog/202403/20240320/20240320-49192.jpg",
        "Venue": "2024.06.08~2024.06.08GS칼텍스 예울마루 대극장",
        "rank": "9위"
    },
    {
        "title": "HIPHOPPLAYA FESTIVAL 2024",
        "ImageURL": "http://tkfile.yes24.com/upload2/perfblog/202405/20240502/20240502-48840.jpg",
        "Venue": "2024.05.04~2024.05.05난지한강공원",
        "rank": "10위"
    }
]